blackjack_multi/__init__.py
blackjack_multi/cards.py
blackjack_multi/game.py
blackjack_multi/player.py
blackjack_multi/types.py
blackjack_multi-0.1.6.dist-info/LICENSE
blackjack_multi-0.1.6.dist-info/METADATA
blackjack_multi-0.1.6.dist-info/WHEEL
blackjack_multi-0.1.6.dist-info/RECORD
