Metadata-Version: 2.1
Name: blackjack-multi
Version: 0.1.6
Summary: a python package for multiplayer blackjack gameplay
Home-page: https://github.com/petersim1/blackjack-pypi
License: MIT
Keywords: blackjack
Author: Peter Simone
Author-email: plssimone@gmail.com
Maintainer: Peter Simone
Maintainer-email: plssimone@gmail.com
Requires-Python: >=3.11,<4.0
Classifier: License :: OSI Approved :: MIT License
Classifier: Programming Language :: Python :: 3
Classifier: Programming Language :: Python :: 3.11
Classifier: Programming Language :: Python :: 3.12
Requires-Dist: pydantic (>=2.7.1,<3.0.0)
Project-URL: Repository, https://github.com/petersim1/blackjack-pypi
